udini_s3_tools/__init__.py
udini_s3_tools/tools_module.py
udini_s3_tools-1.0.1.dist-info/LICENSE
udini_s3_tools-1.0.1.dist-info/METADATA
udini_s3_tools-1.0.1.dist-info/WHEEL
udini_s3_tools-1.0.1.dist-info/top_level.txt
udini_s3_tools-1.0.1.dist-info/RECORD
