Metadata-Version: 2.1
Name: udini_s3_tools
Version: 1.0.1
Summary: A package for Udini services to read/write on s3
Home-page: https://github.com/pypa/udini_s3_tools
Author: Udini.co
Author-email: bouzguenda.medfiras@gmail.com
Project-URL: Bug Tracker, https://github.com/pypa/udini_s3_tools/issues
Classifier: Programming Language :: Python :: 3
Classifier: License :: OSI Approved :: MIT License
Classifier: Operating System :: OS Independent
Requires-Python: >=3.8
License-File: LICENSE
Provides-Extra: dev
Requires-Dist: black ; extra == 'dev'
Requires-Dist: flake8 ; extra == 'dev'
Requires-Dist: pytest ; extra == 'dev'
